vpype_gscrib/__init__.py
vpype_gscrib/config/__init__.py
vpype_gscrib/config/base_config.py
vpype_gscrib/config/builder_config.py
vpype_gscrib/config/config_loader.py
vpype_gscrib/config/config_option.py
vpype_gscrib/config/custom_fields.py
vpype_gscrib/config/render_config.py
vpype_gscrib/enums/__init__.py
vpype_gscrib/enums/types/__init__.py
vpype_gscrib/enums/types/bed_type.py
vpype_gscrib/enums/types/coolant_type.py
vpype_gscrib/enums/types/fan_type.py
vpype_gscrib/enums/types/head_type.py
vpype_gscrib/enums/types/rack_type.py
vpype_gscrib/enums/types/tool_type.py
vpype_gscrib/excepts/__init__.py
vpype_gscrib/excepts/plugin_errors.py
vpype_gscrib/heightmaps/__init__.py
vpype_gscrib/heightmaps/base_heightmap.py
vpype_gscrib/heightmaps/flat_heightmap.py
vpype_gscrib/heightmaps/raster_heightmap.py
vpype_gscrib/heightmaps/sparse_heightmap.py
vpype_gscrib/processor/__init__.py
vpype_gscrib/processor/document_processor.py
vpype_gscrib/processor/document_renderer.py
vpype_gscrib/renderer/__init__.py
vpype_gscrib/renderer/beds/__init__.py
vpype_gscrib/renderer/beds/base_bed.py
vpype_gscrib/renderer/beds/bed_factory.py
vpype_gscrib/renderer/beds/heated_bed.py
vpype_gscrib/renderer/beds/no_bed.py
vpype_gscrib/renderer/coolants/__init__.py
vpype_gscrib/renderer/coolants/base_coolant.py
vpype_gscrib/renderer/coolants/coolant_factory.py
vpype_gscrib/renderer/coolants/flood_coolant.py
vpype_gscrib/renderer/coolants/mist_coolant.py
vpype_gscrib/renderer/coolants/no_coolant.py
vpype_gscrib/renderer/fans/__init__.py
vpype_gscrib/renderer/fans/base_fan.py
vpype_gscrib/renderer/fans/cooling_fan.py
vpype_gscrib/renderer/fans/fan_factory.py
vpype_gscrib/renderer/fans/no_fan.py
vpype_gscrib/renderer/gcode_context.py
vpype_gscrib/renderer/gcode_renderer.py
vpype_gscrib/renderer/heads/__init__.py
vpype_gscrib/renderer/heads/auto_leveling_head.py
vpype_gscrib/renderer/heads/base_head.py
vpype_gscrib/renderer/heads/head_factory.py
vpype_gscrib/renderer/heads/standard_head.py
vpype_gscrib-1.1.1.dist-info/LICENSE
vpype_gscrib-1.1.1.dist-info/METADATA
vpype_gscrib-1.1.1.dist-info/WHEEL
vpype_gscrib-1.1.1.dist-info/entry_points.txt
vpype_gscrib-1.1.1.dist-info/RECORD
