Metadata-Version: 2.3
Name: vpype_gscrib
Version: 1.1.1
Summary: G-Code generator for Vpype
License: GPL-3.0
Keywords: Vpype,G-code,CNC,3D printing,CAM
Author: Joan Sala
Author-email: contact@joansala.com
Requires-Python: >=3.10,<3.13
Classifier: License :: OSI Approved :: GNU General Public License v3 (GPLv3)
Classifier: Programming Language :: Python :: 3
Classifier: Programming Language :: Python :: 3.10
Classifier: Programming Language :: Python :: 3.11
Classifier: Programming Language :: Python :: 3.12
Requires-Dist: gscrib (>=1.1.0,<1.2.0)
Requires-Dist: numpy (>=2.2.0,<2.3.0)
Requires-Dist: opencv-python (>=4.11.0,<4.12.0)
Requires-Dist: pydantic (>=2.10.0,<2.11.0)
Requires-Dist: pyserial (>=3.5.0,<3.6.0)
Requires-Dist: scikit-image (>=0.25.0,<0.26.0)
Requires-Dist: scipy (>=1.15.0,<1.16.0)
Requires-Dist: typeguard (>=4.4.0,<4.5.0)
Requires-Dist: vpype (>=1.14.0,<1.15.0)
Project-URL: Documentation, https://vpype-gscrib.readthedocs.io
Project-URL: Homepage, https://github.com/joansalasoler/vpype-gscrib
Project-URL: Repository, https://github.com/joansalasoler/vpype-gscrib
